tutorialleigos/__init__.py
tutorialleigos/codigo.py
tutorialleigos-0.1.3.dist-info/METADATA
tutorialleigos-0.1.3.dist-info/WHEEL
tutorialleigos-0.1.3.dist-info/entry_points.txt
tutorialleigos-0.1.3.dist-info/RECORD
